setup.cfg
setup.py
simplebitcoinfuncs/__init__.py
simplebitcoinfuncs/_doctester.py
simplebitcoinfuncs/base58.py
simplebitcoinfuncs/bech32.py
simplebitcoinfuncs/bip32.py
simplebitcoinfuncs/bip39.py
simplebitcoinfuncs/bip39wordlists.py
simplebitcoinfuncs/bitcoin.py
simplebitcoinfuncs/ecmath.py
simplebitcoinfuncs/electrum1.py
simplebitcoinfuncs/electrum2.py
simplebitcoinfuncs/hexhashes.py
simplebitcoinfuncs/miscbitcoinfuncs.py
simplebitcoinfuncs/miscfuncs.py
simplebitcoinfuncs/rfc6979.py
simplebitcoinfuncs/signandverify.py
simplebitcoinfuncs/stealth.py
simplebitcoinfuncs.egg-info/PKG-INFO
simplebitcoinfuncs.egg-info/SOURCES.txt
simplebitcoinfuncs.egg-info/dependency_links.txt
simplebitcoinfuncs.egg-info/requires.txt
simplebitcoinfuncs.egg-info/top_level.txt